{
    "id": 2472444,
    "name": "Unconcious..",
    "author": "Aqilhensem_128",
    "creators": [
        "Aqilhensem_128"
    ],
    "verifier": "frederik_11",
    "verification": "https://youtu.be/4Y1Ndt2p8jg?si=SpmkNJwg5ETYl2rj",
    "percentToQualify": 61,
    "records": [
        {
            "user": "Erik_01216",
            "link": "https://youtu.be/UzCz8s8fa6M?si=YaflfHd15aUOlz8O",
            "percent": 100,
            "hz": 60
        },
        {
            "user": "ramanoo2",
            "link": "https://youtu.be/MfjYo6e5dTM?si=fMA1CSEYwlPjnVF5",
            "percent": 100,
            "hz": 60
        }
    ]
}